ec_topsis/__init__.py
ec_topsis/algorithm/__init__.py
ec_topsis/algorithm/src.py
ec_topsis-1.0.2.dist-info/LICENSE
ec_topsis-1.0.2.dist-info/METADATA
ec_topsis-1.0.2.dist-info/WHEEL
ec_topsis-1.0.2.dist-info/top_level.txt
ec_topsis-1.0.2.dist-info/RECORD
