Metadata-Version: 2.1
Name: ec-topsis
Version: 1.0.2
Summary: The EC-TOPSIS Method - A Committee Approach for Outranking Problems Using Randoms Weights
Home-page: https://github.com/Valdecy/ec_topsis
Author: Valdecy Pereira
Author-email: valdecy.pereira@gmail.com
License: GNU
License-File: LICENSE
Requires-Dist: matplotlib
Requires-Dist: numpy
Requires-Dist: pandas
Requires-Dist: scikit-learn
Requires-Dist: scipy
Requires-Dist: seaborn
